nanodl/__init__.py
nanodl/__src/__init__.py
nanodl/__src/classical/__init__.py
nanodl/__src/classical/bayes.py
nanodl/__src/classical/clustering.py
nanodl/__src/classical/dimensionality_reduction.py
nanodl/__src/classical/dsp.py
nanodl/__src/classical/regression.py
nanodl/__src/experimental/__init__.py
nanodl/__src/experimental/bitlinear.py
nanodl/__src/experimental/gat.py
nanodl/__src/experimental/mamba.py
nanodl/__src/experimental/rlhf.py
nanodl/__src/experimental/tokenizer.py
nanodl/__src/models/__init__.py
nanodl/__src/models/attention.py
nanodl/__src/models/clip.py
nanodl/__src/models/diffusion.py
nanodl/__src/models/gemma.py
nanodl/__src/models/gpt.py
nanodl/__src/models/ijepa.py
nanodl/__src/models/kan.py
nanodl/__src/models/lamda.py
nanodl/__src/models/llama.py
nanodl/__src/models/mistral.py
nanodl/__src/models/mixer.py
nanodl/__src/models/reward.py
nanodl/__src/models/t5.py
nanodl/__src/models/transformer.py
nanodl/__src/models/vit.py
nanodl/__src/models/whisper.py
nanodl/__src/utils/__init__.py
nanodl/__src/utils/data.py
nanodl/__src/utils/ml.py
nanodl/__src/utils/nlp.py
nanodl/__src/utils/random.py
nanodl/__src/utils/vision.py
nanodl-0.0.0.dist-info/LICENSE
nanodl-0.0.0.dist-info/METADATA
nanodl-0.0.0.dist-info/WHEEL
nanodl-0.0.0.dist-info/top_level.txt
nanodl-0.0.0.dist-info/RECORD
