Metadata-Version: 2.1
Name: nanodl
Version: 0.0.0
Summary: A Jax-based library for designing and training transformer models from scratch.
Home-page: https://github.com/hmunachi/nanodl
Author: Henry Ndubuaku
Author-email: ndubuakuhenry@gmail.com
Keywords: transformers jax machine learning deep learning pytorch tensorflow
Classifier: Development Status :: 3 - Alpha
Classifier: Intended Audience :: Developers
Classifier: Intended Audience :: Science/Research
Classifier: Intended Audience :: Education
Classifier: Topic :: Software Development :: Build Tools
Classifier: Topic :: Scientific/Engineering :: Artificial Intelligence
Classifier: License :: OSI Approved :: MIT License
Classifier: Programming Language :: Python :: 3
Classifier: Programming Language :: Python :: 3.7
Classifier: Programming Language :: Python :: 3.8
Classifier: Programming Language :: Python :: 3.9
Requires-Python: >=3.7
License-File: LICENSE
Requires-Dist: flax
Requires-Dist: jax
Requires-Dist: jaxlib
Requires-Dist: optax
Requires-Dist: einops
Requires-Dist: sentencepiece
